{
  "key": "irons_ice_upgrade_orb",
  "hidden": false,
  "category": "socket",
  "primary": 0,
  "secondary": 0,
  "tertiary": 0,
  "durability": 0,
  "integrityCost": 3,
  "integrityGain": 0,
  "magicCapacity": 0,
  "toolLevel": 0,
  "toolEfficiency": 0,
  "tints": {
    "glyph": "c5fff6",
    "texture": "c5fff6"
  },
  "textures": [
    "perk_glow_0",
    "perk_sided_0"
  ],
  "material": {
    "items": [
      "irons_spellbooks:ice_upgrade_orb"
    ]
  },
  "experienceCost": 20,
  "attributes": {
    "irons_spellbooks:ice_spell_power": 0.3
  }
}